maseval/__init__.py
maseval-0.3.0.dist-info/licenses/LICENSE
maseval-0.3.0.dist-info/METADATA
maseval-0.3.0.dist-info/WHEEL
maseval-0.3.0.dist-info/top_level.txt
maseval-0.3.0.dist-info/RECORD
