Metadata-Version: 2.4
Name: maseval
Version: 0.3.0
Summary: A library for multi-agent systems evaluation and benchmarking.
Author-email: Cornelius Emde <cornelius@parameterlab.de>
License: MIT License
Project-URL: Homepage, https://github.com/parameterlab/MASEval
Project-URL: Bug Tracker, https://github.com/parameterlab/MASEval/issues
Project-URL: Documentation, https://maseval.readthedocs.io/en/stable/
Project-URL: Changelog, https://github.com/parameterlab/MASEval/blob/main/CHANGELOG.md
Classifier: Development Status :: 3 - Alpha
Classifier: Intended Audience :: Science/Research
Classifier: License :: OSI Approved :: MIT License
Classifier: Programming Language :: Python :: 3
Classifier: Programming Language :: Python :: 3.10
Classifier: Programming Language :: Python :: 3.11
Classifier: Programming Language :: Python :: 3.12
Classifier: Programming Language :: Python :: 3.13
Classifier: Topic :: Scientific/Engineering :: Artificial Intelligence
Requires-Python: >=3.10
License-File: LICENSE
Requires-Dist: gitpython>=3.1.0
Requires-Dist: tqdm>=4.66.0
Requires-Dist: rich>=14.1.0
Requires-Dist: pydantic>=2.12.5
Provides-Extra: smolagents
Requires-Dist: smolagents>=1.21.3; extra == "smolagents"
Provides-Extra: langgraph
Requires-Dist: langgraph>=0.6.0; extra == "langgraph"
Provides-Extra: llamaindex
Requires-Dist: llama-index-core>=0.12.0; extra == "llamaindex"
Provides-Extra: anthropic
Requires-Dist: anthropic>=0.40.0; extra == "anthropic"
Provides-Extra: openai
Requires-Dist: openai>=1.107.2; extra == "openai"
Provides-Extra: google-genai
Requires-Dist: google-genai>=1.37.0; extra == "google-genai"
Provides-Extra: transformers
Requires-Dist: transformers>=4.37.0; extra == "transformers"
Provides-Extra: litellm
Requires-Dist: litellm>=1.0.0; extra == "litellm"
Provides-Extra: wandb
Requires-Dist: wandb>=0.15.0; extra == "wandb"
Provides-Extra: langfuse
Requires-Dist: langfuse>=3.3.4; extra == "langfuse"
Provides-Extra: examples
Requires-Dist: maseval[anthropic,google-genai,langfuse,langgraph,litellm,llamaindex,openai,smolagents]; extra == "examples"
Requires-Dist: langchain>=0.3.27; extra == "examples"
Requires-Dist: langchain-google-genai>=2.1.12; extra == "examples"
Requires-Dist: typing-extensions>=4.0.0; extra == "examples"
Requires-Dist: mcp>=1.22.0; extra == "examples"
Requires-Dist: python-dotenv>=1.0.0; extra == "examples"
Requires-Dist: jupyter>=1.0.0; extra == "examples"
Requires-Dist: ipykernel>=6.0.0; extra == "examples"
Requires-Dist: ipywidgets>=8.0.0; extra == "examples"
Provides-Extra: all
Requires-Dist: maseval[examples,transformers,wandb]; extra == "all"
Dynamic: license-file
